srproject.py
srproject-1.3.0.dist-info/METADATA
srproject-1.3.0.dist-info/WHEEL
srproject-1.3.0.dist-info/top_level.txt
srproject-1.3.0.dist-info/RECORD
