Metadata-Version: 2.1
Name: srproject
Version: 1.3.0
Summary: nested 리스트를 간단하게 출력하기
Home-page: https://hanminwoo.com/
Author: smallrich
Author-email: hanminwoo0306@gmail.com
License: MIT
Platform: UNKNOWN
Classifier: Programming Language :: Python :: 3
Classifier: License :: OSI Approved :: MIT License
Classifier: Operating System :: OS Independent
